learna_tools/__init__.py
learna_tools/data.py
learna_tools/visualization.py
learna_tools/learna/__init__.py
learna_tools/learna/agent.py
learna_tools/learna/design_rna_inference_only.py
learna_tools/learna/environment.py
learna_tools/learna/environment_test.py
learna_tools/learna/learn_to_design_rna.py
learna_tools/learna/data/__init__.py
learna_tools/learna/data/download_and_build_eterna.py
learna_tools/learna/data/parse_dot_brackets.py
learna_tools/learna/optimization/__init__.py
learna_tools/learna/optimization/bohb.py
learna_tools/learna/optimization/learna_worker.py
learna_tools/learna/optimization/meta_learna_worker.py
learna_tools/liblearna/__init__.py
learna_tools/liblearna/agent.py
learna_tools/liblearna/design_rna.py
learna_tools/liblearna/design_rna_inference_only.py
learna_tools/liblearna/environment.py
learna_tools/liblearna/learn_to_design_rna.py
learna_tools/liblearna/data/RNAct.py
learna_tools/liblearna/data/__init__.py
learna_tools/liblearna/data/basis.py
learna_tools/liblearna/data/download_and_build_eterna.py
learna_tools/liblearna/data/generate_anta_data.py
learna_tools/liblearna/data/generate_anta_partial_balanced_data.py
learna_tools/liblearna/data/generate_rfam_dataset.py
learna_tools/liblearna/data/generate_rfam_interim.py
learna_tools/liblearna/data/generate_rfam_taneda_local.py
learna_tools/liblearna/data/interim_to_single_files.py
learna_tools/liblearna/data/parse_dot_brackets.py
learna_tools/liblearna/data/translate_balanced_data_for_learna.py
learna_tools/liblearna/data/validate_datasets.py
learna_tools/liblearna/optimization/__init__.py
learna_tools/liblearna/optimization/bohb.py
learna_tools/liblearna/optimization/bohb_load.py
learna_tools/liblearna/optimization/learna_worker.py
learna_tools/liblearna/optimization/meta_learna_adapt_worker.py
learna_tools/liblearna/optimization/meta_learna_worker.py
learna_tools/liblearna/optimization/bohb_worker/LEARNA.py
learna_tools/liblearna/optimization/bohb_worker/MetaLEARNA.py
learna_tools-0.1.0.dist-info/LICENSE
learna_tools-0.1.0.dist-info/METADATA
learna_tools-0.1.0.dist-info/WHEEL
learna_tools-0.1.0.dist-info/top_level.txt
learna_tools-0.1.0.dist-info/RECORD
