Metadata-Version: 2.1
Name: learna-tools
Version: 0.1.0
Summary: RNA Design with automated reinforcement learning.
Home-page: https://github.com/automl/learna_tools.git
Author: Frederic Runge
Author-email: runget@cs.uni-freiburg.de
License: MIT
Keywords: RNA Design
Platform: UNKNOWN
Classifier: Programming Language :: Python :: 3.6
License-File: LICENSE
Requires-Dist: Distance
Requires-Dist: GraKeL (==0.1.8)
Requires-Dist: numpy
Requires-Dist: pandas
Requires-Dist: pyaml
Requires-Dist: pynisher
Requires-Dist: pytest
Requires-Dist: pylint
Requires-Dist: psutil
Requires-Dist: configspace
Requires-Dist: scipy
Requires-Dist: Sphinx
Requires-Dist: tensorflow (==1.4.0)
Requires-Dist: scikits.bootstrap
Requires-Dist: hpbandster
Requires-Dist: tqdm
Requires-Dist: black
Requires-Dist: tensorforce (==0.3.3)
Requires-Dist: dataclasses
Requires-Dist: munch
Requires-Dist: pyyaml
Requires-Dist: scikit-learn
Requires-Dist: LinearFold
Requires-Dist: tabulate
Requires-Dist: matplotlib
Requires-Dist: biopython
Requires-Dist: logomaker
